{
    "surveyName": "Rapid Appraisal Survey",
    "sections": [
        {
            "id": 1,
            "name": "Administration",
            "branches": [
                {
                    "expandable": false,
                    "questions": [
                        {
                            "id": 1,
                            "text": "Date of Survey",
                            "type": "Date"
                        },
                        {
                            "id": 2,
                            "text": "Name of Surveyor(s) who checked the map:",
                            "type": "SmallFree"
                        },
                        {
                            "id": 3,
                            "text": "Name of Surveyor(s) who collected the data:",
                            "type": "SmallFree"
                        },
                        {
                            "id": 4,
                            "text": "Name of Surveyor(s) who took the photograps:",
                            "type": "SmallFree"
                        }
                    ]
                }
            ]
        },
        {
            "id": 2,
            "name": "General Information",
            "branches": [
                {
                    "expandable": false,
                    "questions": [
                        {
                            "id": 1,
                            "text": "State",
                            "type": "SmallFree",
                            "readOnly": true,
                            "default": "27"
                        },
                        {
                            "id": 2,
                            "text": "District",
                            "type": "SmallFree",
                            "readOnly": true,
                            "default": "25"
                        },
                        {
                            "id": 3,
                            "text": "City",
                            "type": "SmallFree",
                            "minLength": 4,
                            "maxLength": 4
                        },
                        {
                            "id": 4,
                            "text": "Electoral",
                            "type": "SmallFree",
                            "minLength": 2,
                            "maxLength": 2
                        },
                        {
                            "id": 5,
                            "text": "Slum",
                            "type": "SmallFree",
                            "minLength": 2,
                            "maxLength": 2
                        },
                        {
                            "id": 5,
                            "text": "HouseHold",
                            "type": "SmallFree",
                            "readOnly": true,
                            "default": "N/A"
                        },
                        {
                            "id": 6,
                            "text": "Survey #:",
                            "type": "SmallFree"
                        },
                        {
                            "id": 7,
                            "text": "Slum Name:",
                            "type": "SmallFree"
                        },
                        {
                            "id": 8,
                            "text": "Administrative Ward #:",
                            "type": "SmallFree"
                        },
                        {
                            "id": 9,
                            "text": "Administrative Ward Name:",
                            "type": "SmallFree"
                        },
                        {
                            "id": 10,
                            "text": "Electoral Ward #:",
                            "type": "SmallFree"
                        },
                        {
                            "id": 11,
                            "text": "Electoral Ward Name:",
                            "type": "SmallFree"
                        },
                        {
                            "id": 12,
                            "text": "Landmark:",
                            "type": "SmallFree"
                        },
                        {
                            "id": 13,
                            "text": "PMC SRA Zone:",
                            "type": "Dropdown",
                            "choices":[ 
                            	{"1": "A"},
                                {"2": "B"},
                                {"3": "C"},
                                {"4": "D"}
                                ]
                        },
                        {
                            "id": 14,
                            "text": "Ration Ward #",
                            "type": "SmallFree"
                        },
                        {
                            "id": 15,
                            "text": "Ration Ward Name:",
                            "type": "SmallFree"
                        },
                        {
                            "id": 16,
                            "text": "Year established according to the community:",
                            "type": "SmallFree"
                        },
                        {
                            "id": 17,
                            "text": "Year established according to The Pune Municipal Corporation(PMC):",
                            "type": "SmallFree"
                        },
                        {
                            "id": 18,
                            "text": "Legal Status:",
                            "type": "Dropdown",
                            "choices": [
                                {"1": "Undeclared"},
                                {"2": "Partly Declared"},
                                {"3": "Declared"}
                            ]
                        },
                        {
                            "id": 19,
                            "text": "Date of declaration:",
                            "type": "Date"
                        },
                        {
                            "id": 20,
                            "text": "Land Owner:",
                            "type": "Tickbox",
                            "choices": [
                               { "1": "Private"},
                               { "2": "Central Government"},
                               { "3": "State Government"},
                               { "4": "Local Government(PMC)"}
                            ]
                        },
                        {
                            "id": 21,
                            "text": "Development Plan Reservations:",
                            "type": "Tickbox",
                            "choices": [
                               { "1": "Road Widening" },
                               { "2": "Open Space/Garden/Green Belt/BDP" },
                               { "3": "School" },
                               { "4": "Hospital" },
                               { "5": "Library" },
                               { "6": "Economically Weaker Section" },
                               { "7": "No reservation" }
                            ]
                        },
                        {
                            "id": 22,
                            "text": "Development Plan Land Use:",
                            "type": "Tickbox",
                            "choices": [
                               { "1": "Residential" },
                               { "2": "Commercial"},
                               { "3": "Industrial" },
                               { "4": "Public- Semi Public" },
                               { "5": "Public Utility" },
                               { "6": "Recreational/Open Space" },
                               { "7": "Agricultural" },
                               { "8": "River/Water body"}
                            ]
                        },
                        {
                            "id": 23,
                            "text": "Approxomite are of the settlement in square meters:",
                            "type": "SmallFree"
                        },
                        {
                            "id": 24,
                            "text": "Approxomate number of huts in the settlement",
                            "type": "Dropdown",
                            "choices": [
                                {"1": "Less than 150"},
                                {"2": "150-300"},
                                {"3": "300-500"},
                                {"4": "500-1000"},
                                {"5": "1000+" }
                            ]
                        },
                        {
                            "id": 25,
                            "text": "Location",
                            "type": "Tickbox",
                            "choices": [
                               { "1": "Water body/river bed/canal"},
                               { "2": "Hill slope"},
                               { "3": "Main road"},
                               { "4": "Railway line"},
                               { "5": "Within 1kn of an airport"},
                               { "6": "Isolated"}
                            ]
                        },
                        {
                            "id": 26,
                            "text": "Topography",
                            "type": "Tickbox",
                            "choices": [
                               { "1": "Acute"},
                               { "2": "Reasonable"},
                               { "3": "Slight"},
                               { "4": "Flat"}
                            ]
                        }
                    ]
                }
            ]
        },
        {
            "id": 3,
            "name": "Toilet Information",
            "branches": [
                {
                    "expandable": false,
                    "questions": [
                        {
                            "id": 1,
                            "text": "Number of community toilet blocks:",
                            "type": "SmallFree"
                        },
                        {
                            "id": 2,
                            "text": "Number of 'Pay & Use' community toilet blocks:",
                            "type": "SmallFree"
                        },
                        {
                            "id": 3,
                            "text": "Strategy in addition to community toilet blocks",
                            "type": "Tickbox",
                            "choices": [
                               { "1": "Not applicable"},
                               { "2": "Open Defecation"},
                               { "3": "Public toilets outside of the settlement"},
                               { "4": "Group Toilet"},
                               { "5": "Individual Toilet"}
                            ]
                        }
                    ]
                },
                {
                    "expandable": true,
                    "questions": [
                        {
                            "id": 4,
                            "text": "Community toilet cost(per month, in rupees)",
                            "type": "SmallFree"
                        },
                        {
                            "id": 5,
                            "text": "Cost of 'Pay&Use' toilets (per individual use, in rupees)",
                            "type": "SmallFree"
                        },
                        {
                            "id": 6,
                            "text": "Cost of 'Pay&Use' toilets (per family per month, in rupees)",
                            "type": "SmallFree"
                        },
                        {
                            "id": 7,
                            "text": "Toilet blocks gender usage",
                            "type": "Dropdown",
                            "choices": [
                               { "1": "Male" },
                               { "2": "Female"},
                               { "3": "Mixed"}
                            ]
                        },
                        {
                            "id": 8,
                            "text": "Number of seats used by men",
                            "type": "SmallFree"
                        },
                        {
                            "id": 9,
                            "text": "Number of seats NOT used by men",
                            "type": "SmallFree"
                        },
                        {
                            "id": 10,
                            "text": "The reason for the men not using the seats",
                            "type": "Tickbox",
                            "choices": [
                               { "1": "Not Applicable"},
                               { "2": "Choked"},
                               { "3": "Broken Pan"},
                               { "4": "Broken Door"},
                               { "5": "No Water"},
                               { "6": "No electricity"},
                               { "7": "Poor up-keep"},
                               { "8": "Construction"}
                            ]
                        },
                        {
                            "id": 11,
                            "text": "Number of seats used by women",
                            "type": "SmallFree"
                        },
                        {
                            "id": 12,
                            "text": "Number of seats NOT used by women",
                            "type": "SmallFree"
                        },
                        {
                            "id": 13,
                            "text": "The reason for the women not using the seats",
                            "type": "Tickbox",
                            "choices": [
                              {  "1": "Not Applicable"},
                              {  "2": "Choked"},
                              { "3": "Broken Pan"},
                              {  "4": "Broken Door"},
                              {  "5": "No Water"},
                              {  "6": "No electricity"},
                              {  "7": "Poor up-keep"},
                              {  "8": "Construction"}
                            ]
                        }
                    ]
                }
            ]
        }
    ]
}